oplibcore.pypy310-pp73-x86_64-linux-gnu.so
oplibcore-0.1.3.dist-info/METADATA
oplibcore-0.1.3.dist-info/WHEEL
oplibcore-0.1.3.dist-info/RECORD
oplibcore-0.1.3.dist-info/top_level.txt
oplibcore.libs/libonnxruntime-1747c77e.so.1.17.0
oplibcore.libs/libgfortran-6a8a198e.so.5.0.0
oplibcore.libs/libopenblas_haswellp-r0-3a106fe6.3.24.dev.so
oplibcore.libs/libquadmath-895c7c83.so.0.0.0
