Metadata-Version: 2.1
Name: oplibcore
Version: 0.1.3
Summary: numpy, but better because I made it
Home-page: UNKNOWN
License: UNKNOWN
Platform: UNKNOWN
